{"topicSections":[{"identifiers":["doc:\/\/com.opticalaberration.hummingbird\/documentation\/HummingbirdCore\/FlatDictionary\/init()","doc:\/\/com.opticalaberration.hummingbird\/documentation\/HummingbirdCore\/FlatDictionary\/init(_:)","doc:\/\/com.opticalaberration.hummingbird\/documentation\/HummingbirdCore\/FlatDictionary\/init(dictionaryLiteral:)"],"title":"Initializers"},{"identifiers":["doc:\/\/com.opticalaberration.hummingbird\/documentation\/HummingbirdCore\/FlatDictionary\/endIndex","doc:\/\/com.opticalaberration.hummingbird\/documentation\/HummingbirdCore\/FlatDictionary\/startIndex"],"title":"Instance Properties"},{"identifiers":["doc:\/\/com.opticalaberration.hummingbird\/documentation\/HummingbirdCore\/FlatDictionary\/append(key:value:)","doc:\/\/com.opticalaberration.hummingbird\/documentation\/HummingbirdCore\/FlatDictionary\/get(_:)","doc:\/\/com.opticalaberration.hummingbird\/documentation\/HummingbirdCore\/FlatDictionary\/get(_:as:)-2owlj","doc:\/\/com.opticalaberration.hummingbird\/documentation\/HummingbirdCore\/FlatDictionary\/get(_:as:)-3fdsi","doc:\/\/com.opticalaberration.hummingbird\/documentation\/HummingbirdCore\/FlatDictionary\/get(_:as:)-5ewlr","doc:\/\/com.opticalaberration.hummingbird\/documentation\/HummingbirdCore\/FlatDictionary\/getAll(_:)","doc:\/\/com.opticalaberration.hummingbird\/documentation\/HummingbirdCore\/FlatDictionary\/getAll(_:as:)-261y8","doc:\/\/com.opticalaberration.hummingbird\/documentation\/HummingbirdCore\/FlatDictionary\/getAll(_:as:)-4h655","doc:\/\/com.opticalaberration.hummingbird\/documentation\/HummingbirdCore\/FlatDictionary\/getAll(_:as:)-5ftdw","doc:\/\/com.opticalaberration.hummingbird\/documentation\/HummingbirdCore\/FlatDictionary\/getCatchAll()","doc:\/\/com.opticalaberration.hummingbird\/documentation\/HummingbirdCore\/FlatDictionary\/has(_:)","doc:\/\/com.opticalaberration.hummingbird\/documentation\/HummingbirdCore\/FlatDictionary\/index(after:)","doc:\/\/com.opticalaberration.hummingbird\/documentation\/HummingbirdCore\/FlatDictionary\/require(_:)","doc:\/\/com.opticalaberration.hummingbird\/documentation\/HummingbirdCore\/FlatDictionary\/require(_:as:)-516jy","doc:\/\/com.opticalaberration.hummingbird\/documentation\/HummingbirdCore\/FlatDictionary\/require(_:as:)-8wfem","doc:\/\/com.opticalaberration.hummingbird\/documentation\/HummingbirdCore\/FlatDictionary\/require(_:as:)-zo5p","doc:\/\/com.opticalaberration.hummingbird\/documentation\/HummingbirdCore\/FlatDictionary\/requireAll(_:as:)-3sj8s","doc:\/\/com.opticalaberration.hummingbird\/documentation\/HummingbirdCore\/FlatDictionary\/requireAll(_:as:)-52rco","doc:\/\/com.opticalaberration.hummingbird\/documentation\/HummingbirdCore\/FlatDictionary\/requireAll(_:as:)-8n9if","doc:\/\/com.opticalaberration.hummingbird\/documentation\/HummingbirdCore\/FlatDictionary\/setCatchAll(_:)"],"title":"Instance Methods"},{"identifiers":["doc:\/\/com.opticalaberration.hummingbird\/documentation\/HummingbirdCore\/FlatDictionary\/subscript(_:)-2eyqb","doc:\/\/com.opticalaberration.hummingbird\/documentation\/HummingbirdCore\/FlatDictionary\/subscript(_:)-4wq5d","doc:\/\/com.opticalaberration.hummingbird\/documentation\/HummingbirdCore\/FlatDictionary\/subscript(values:)"],"title":"Subscripts"},{"identifiers":["doc:\/\/com.opticalaberration.hummingbird\/documentation\/HummingbirdCore\/FlatDictionary\/Element","doc:\/\/com.opticalaberration.hummingbird\/documentation\/HummingbirdCore\/FlatDictionary\/Index"],"title":"Type Aliases"},{"identifiers":["doc:\/\/com.opticalaberration.hummingbird\/documentation\/HummingbirdCore\/FlatDictionary\/recursiveCaptureKey"],"title":"Type Properties"},{"generated":true,"identifiers":["doc:\/\/com.opticalaberration.hummingbird\/documentation\/HummingbirdCore\/FlatDictionary\/Collection-Implementations","doc:\/\/com.opticalaberration.hummingbird\/documentation\/HummingbirdCore\/FlatDictionary\/Sequence-Implementations"],"title":"Default Implementations"}],"primaryContentSections":[{"kind":"declarations","declarations":[{"platforms":["Linux"],"languages":["swift"],"tokens":[{"text":"struct","kind":"keyword"},{"text":" ","kind":"text"},{"text":"FlatDictionary","kind":"identifier"},{"text":"<","kind":"text"},{"text":"Key","kind":"genericParameter"},{"text":", ","kind":"text"},{"text":"Value","kind":"genericParameter"},{"text":"> ","kind":"text"},{"text":"where","kind":"keyword"},{"text":" ","kind":"text"},{"text":"Key","kind":"typeIdentifier"},{"text":" : ","kind":"text"},{"text":"Hashable","preciseIdentifier":"s:SH","kind":"typeIdentifier"}]}]},{"kind":"content","content":[{"anchor":"overview","text":"Overview","type":"heading","level":2},{"type":"paragraph","inlineContent":[{"type":"text","text":"Useful for dictionary lookup on small collection that don’t need"},{"type":"text","text":" "},{"type":"text","text":"a tree lookup to optimise indexing."}]},{"type":"paragraph","inlineContent":[{"type":"text","text":"The FlatDictionary also allows for key clashes. Standard lookup"},{"type":"text","text":" "},{"type":"text","text":"functions will always return the first key found, but if you"},{"type":"text","text":" "},{"type":"text","text":"iterate through the key,value pairs you can access all values"},{"type":"text","text":" "},{"type":"text","text":"for a key"}]}]}],"hierarchy":{"paths":[["doc:\/\/com.opticalaberration.hummingbird\/documentation\/HummingbirdCore"]]},"abstract":[{"type":"text","text":"Provides Dictionary like indexing, but uses a flat array of key"},{"type":"text","text":" "},{"type":"text","text":"value pairs, plus an array of hash keys for lookup for storage."}],"kind":"symbol","sections":[],"variants":[{"traits":[{"interfaceLanguage":"swift"}],"paths":["\/documentation\/hummingbirdcore\/flatdictionary"]}],"metadata":{"externalID":"s:15HummingbirdCore14FlatDictionaryV","navigatorTitle":[{"kind":"identifier","text":"FlatDictionary"}],"fragments":[{"kind":"keyword","text":"struct"},{"kind":"text","text":" "},{"kind":"identifier","text":"FlatDictionary"}],"role":"symbol","symbolKind":"struct","roleHeading":"Structure","modules":[{"name":"HummingbirdCore"}],"title":"FlatDictionary"},"schemaVersion":{"patch":0,"major":0,"minor":3},"identifier":{"url":"doc:\/\/com.opticalaberration.hummingbird\/documentation\/HummingbirdCore\/FlatDictionary","interfaceLanguage":"swift"},"relationshipsSections":[{"type":"conformsTo","kind":"relationships","identifiers":["doc:\/\/com.opticalaberration.hummingbird\/Sl","doc:\/\/com.opticalaberration.hummingbird\/s30ExpressibleByDictionaryLiteralP","doc:\/\/com.opticalaberration.hummingbird\/s8SendableP","doc:\/\/com.opticalaberration.hummingbird\/ST"],"title":"Conforms To"}],"references":{"doc://com.opticalaberration.hummingbird/documentation/HummingbirdCore/FlatDictionary/get(_:as:)-3fdsi":{"abstract":[{"type":"text","text":"Return parameter with specified id as a certain type"}],"type":"topic","kind":"symbol","role":"symbol","title":"get(_:as:)","fragments":[{"kind":"keyword","text":"func"},{"kind":"text","text":" "},{"kind":"identifier","text":"get"},{"kind":"text","text":"<"},{"kind":"genericParameter","text":"T"},{"kind":"text","text":">("},{"preciseIdentifier":"s:SS","kind":"typeIdentifier","text":"String"},{"kind":"text","text":", "},{"kind":"externalParam","text":"as"},{"text":": ","kind":"text"},{"preciseIdentifier":"s:15HummingbirdCore14FlatDictionaryV0A0SsRszSsRs_rlE3get_2asqd__SgSS_qd__mts25LosslessStringConvertibleRd__lF1TL_qd__mfp","text":"T","kind":"typeIdentifier"},{"text":".Type) -> ","kind":"text"},{"preciseIdentifier":"s:15HummingbirdCore14FlatDictionaryV0A0SsRszSsRs_rlE3get_2asqd__SgSS_qd__mts25LosslessStringConvertibleRd__lF1TL_qd__mfp","text":"T","kind":"typeIdentifier"},{"text":"?","kind":"text"}],"identifier":"doc:\/\/com.opticalaberration.hummingbird\/documentation\/HummingbirdCore\/FlatDictionary\/get(_:as:)-3fdsi","url":"\/documentation\/hummingbirdcore\/flatdictionary\/get(_:as:)-3fdsi","conformance":{"constraints":[{"type":"codeVoice","code":"Key"},{"text":" is ","type":"text"},{"type":"codeVoice","code":"Substring"},{"text":" and ","type":"text"},{"type":"codeVoice","code":"Value"},{"text":" is ","type":"text"},{"type":"codeVoice","code":"Substring"},{"text":".","type":"text"}],"conformancePrefix":[{"text":"Conforms when","type":"text"}],"availabilityPrefix":[{"text":"Available when","type":"text"}]}},"doc://com.opticalaberration.hummingbird/s8SendableP":{"type":"unresolvable","title":"Swift.Sendable","identifier":"doc:\/\/com.opticalaberration.hummingbird\/s8SendableP"},"doc://com.opticalaberration.hummingbird/documentation/HummingbirdCore/FlatDictionary/subscript(_:)-4wq5d":{"fragments":[{"text":"subscript","kind":"keyword"},{"text":"(","kind":"text"},{"preciseIdentifier":"s:15HummingbirdCore14FlatDictionaryV5Indexa","text":"Index","kind":"typeIdentifier"},{"text":") -> ","kind":"text"},{"preciseIdentifier":"s:15HummingbirdCore14FlatDictionaryV7Elementa","text":"Element","kind":"typeIdentifier"}],"abstract":[{"type":"text","text":"Access element at specific position"}],"role":"symbol","url":"\/documentation\/hummingbirdcore\/flatdictionary\/subscript(_:)-4wq5d","kind":"symbol","type":"topic","title":"subscript(_:)","identifier":"doc:\/\/com.opticalaberration.hummingbird\/documentation\/HummingbirdCore\/FlatDictionary\/subscript(_:)-4wq5d"},"doc://com.opticalaberration.hummingbird/documentation/HummingbirdCore/FlatDictionary":{"title":"FlatDictionary","type":"topic","role":"symbol","abstract":[{"type":"text","text":"Provides Dictionary like indexing, but uses a flat array of key"},{"type":"text","text":" "},{"type":"text","text":"value pairs, plus an array of hash keys for lookup for storage."}],"fragments":[{"kind":"keyword","text":"struct"},{"kind":"text","text":" "},{"kind":"identifier","text":"FlatDictionary"}],"identifier":"doc:\/\/com.opticalaberration.hummingbird\/documentation\/HummingbirdCore\/FlatDictionary","navigatorTitle":[{"kind":"identifier","text":"FlatDictionary"}],"kind":"symbol","url":"\/documentation\/hummingbirdcore\/flatdictionary"},"doc://com.opticalaberration.hummingbird/documentation/HummingbirdCore/FlatDictionary/index(after:)":{"kind":"symbol","url":"\/documentation\/hummingbirdcore\/flatdictionary\/index(after:)","abstract":[{"text":"Returns the index immediately after the given index","type":"text"}],"title":"index(after:)","type":"topic","role":"symbol","identifier":"doc:\/\/com.opticalaberration.hummingbird\/documentation\/HummingbirdCore\/FlatDictionary\/index(after:)","fragments":[{"text":"func","kind":"keyword"},{"text":" ","kind":"text"},{"text":"index","kind":"identifier"},{"text":"(","kind":"text"},{"text":"after","kind":"externalParam"},{"text":": ","kind":"text"},{"text":"Index","preciseIdentifier":"s:15HummingbirdCore14FlatDictionaryV5Indexa","kind":"typeIdentifier"},{"text":") -> ","kind":"text"},{"text":"Index","preciseIdentifier":"s:15HummingbirdCore14FlatDictionaryV5Indexa","kind":"typeIdentifier"}]},"doc://com.opticalaberration.hummingbird/ST":{"type":"unresolvable","title":"Swift.Sequence","identifier":"doc:\/\/com.opticalaberration.hummingbird\/ST"},"doc://com.opticalaberration.hummingbird/documentation/HummingbirdCore/FlatDictionary/require(_:as:)-516jy":{"kind":"symbol","title":"require(_:as:)","url":"\/documentation\/hummingbirdcore\/flatdictionary\/require(_:as:)-516jy","identifier":"doc:\/\/com.opticalaberration.hummingbird\/documentation\/HummingbirdCore\/FlatDictionary\/require(_:as:)-516jy","type":"topic","abstract":[{"text":"Return parameter with specified id as a certain type","type":"text"}],"fragments":[{"text":"func","kind":"keyword"},{"text":" ","kind":"text"},{"text":"require","kind":"identifier"},{"text":"(","kind":"text"},{"text":"String","preciseIdentifier":"s:SS","kind":"typeIdentifier"},{"text":", ","kind":"text"},{"text":"as","kind":"externalParam"},{"text":": ","kind":"text"},{"text":"UUID","preciseIdentifier":"s:10Foundation4UUIDV","kind":"typeIdentifier"},{"text":".Type) ","kind":"text"},{"text":"throws","kind":"keyword"},{"text":" -> ","kind":"text"},{"text":"UUID","preciseIdentifier":"s:10Foundation4UUIDV","kind":"typeIdentifier"}],"conformance":{"availabilityPrefix":[{"text":"Available when","type":"text"}],"conformancePrefix":[{"text":"Conforms when","type":"text"}],"constraints":[{"type":"codeVoice","code":"Key"},{"text":" is ","type":"text"},{"type":"codeVoice","code":"Substring"},{"text":" and ","type":"text"},{"type":"codeVoice","code":"Value"},{"text":" is ","type":"text"},{"type":"codeVoice","code":"Substring"},{"text":".","type":"text"}]},"role":"symbol"},"doc://com.opticalaberration.hummingbird/documentation/HummingbirdCore/FlatDictionary/startIndex":{"kind":"symbol","role":"symbol","type":"topic","url":"\/documentation\/hummingbirdcore\/flatdictionary\/startindex","abstract":[{"text":"The position of the first element","type":"text"}],"title":"startIndex","fragments":[{"text":"var","kind":"keyword"},{"text":" ","kind":"text"},{"text":"startIndex","kind":"identifier"},{"text":": ","kind":"text"},{"text":"Index","preciseIdentifier":"s:15HummingbirdCore14FlatDictionaryV5Indexa","kind":"typeIdentifier"}],"identifier":"doc:\/\/com.opticalaberration.hummingbird\/documentation\/HummingbirdCore\/FlatDictionary\/startIndex"},"doc://com.opticalaberration.hummingbird/documentation/HummingbirdCore/FlatDictionary/getAll(_:as:)-5ftdw":{"type":"topic","abstract":[{"type":"text","text":"Return parameter with specified id as a certain type"}],"kind":"symbol","identifier":"doc:\/\/com.opticalaberration.hummingbird\/documentation\/HummingbirdCore\/FlatDictionary\/getAll(_:as:)-5ftdw","url":"\/documentation\/hummingbirdcore\/flatdictionary\/getall(_:as:)-5ftdw","title":"getAll(_:as:)","conformance":{"availabilityPrefix":[{"text":"Available when","type":"text"}],"constraints":[{"code":"Key","type":"codeVoice"},{"text":" is ","type":"text"},{"code":"Substring","type":"codeVoice"},{"text":" and ","type":"text"},{"code":"Value","type":"codeVoice"},{"text":" is ","type":"text"},{"code":"Substring","type":"codeVoice"},{"text":".","type":"text"}],"conformancePrefix":[{"text":"Conforms when","type":"text"}]},"role":"symbol","fragments":[{"kind":"keyword","text":"func"},{"kind":"text","text":" "},{"kind":"identifier","text":"getAll"},{"kind":"text","text":"("},{"preciseIdentifier":"s:SS","kind":"typeIdentifier","text":"String"},{"kind":"text","text":", "},{"kind":"externalParam","text":"as"},{"kind":"text","text":": "},{"preciseIdentifier":"s:10Foundation4UUIDV","kind":"typeIdentifier","text":"UUID"},{"kind":"text","text":".Type) -> ["},{"preciseIdentifier":"s:10Foundation4UUIDV","kind":"typeIdentifier","text":"UUID"},{"kind":"text","text":"]"}]},"doc://com.opticalaberration.hummingbird/documentation/HummingbirdCore/FlatDictionary/Sequence-Implementations":{"type":"topic","url":"\/documentation\/hummingbirdcore\/flatdictionary\/sequence-implementations","role":"collectionGroup","kind":"article","identifier":"doc:\/\/com.opticalaberration.hummingbird\/documentation\/HummingbirdCore\/FlatDictionary\/Sequence-Implementations","title":"Sequence Implementations","abstract":[]},"doc://com.opticalaberration.hummingbird/documentation/HummingbirdCore/FlatDictionary/endIndex":{"kind":"symbol","type":"topic","fragments":[{"text":"var","kind":"keyword"},{"text":" ","kind":"text"},{"text":"endIndex","kind":"identifier"},{"text":": ","kind":"text"},{"text":"Index","preciseIdentifier":"s:15HummingbirdCore14FlatDictionaryV5Indexa","kind":"typeIdentifier"}],"url":"\/documentation\/hummingbirdcore\/flatdictionary\/endindex","role":"symbol","title":"endIndex","identifier":"doc:\/\/com.opticalaberration.hummingbird\/documentation\/HummingbirdCore\/FlatDictionary\/endIndex","abstract":[{"type":"text","text":"The position of the element just after the last element"}]},"doc://com.opticalaberration.hummingbird/documentation/HummingbirdCore/FlatDictionary/Collection-Implementations":{"type":"topic","abstract":[],"kind":"article","role":"collectionGroup","title":"Collection Implementations","url":"\/documentation\/hummingbirdcore\/flatdictionary\/collection-implementations","identifier":"doc:\/\/com.opticalaberration.hummingbird\/documentation\/HummingbirdCore\/FlatDictionary\/Collection-Implementations"},"doc://com.opticalaberration.hummingbird/documentation/HummingbirdCore/FlatDictionary/Element":{"type":"topic","abstract":[],"kind":"symbol","role":"symbol","fragments":[{"text":"typealias","kind":"keyword"},{"text":" ","kind":"text"},{"text":"Element","kind":"identifier"}],"title":"FlatDictionary.Element","url":"\/documentation\/hummingbirdcore\/flatdictionary\/element","identifier":"doc:\/\/com.opticalaberration.hummingbird\/documentation\/HummingbirdCore\/FlatDictionary\/Element","navigatorTitle":[{"kind":"identifier","text":"Element"}]},"doc://com.opticalaberration.hummingbird/documentation/HummingbirdCore/FlatDictionary/requireAll(_:as:)-3sj8s":{"fragments":[{"text":"func","kind":"keyword"},{"text":" ","kind":"text"},{"text":"requireAll","kind":"identifier"},{"text":"(","kind":"text"},{"preciseIdentifier":"s:SS","text":"String","kind":"typeIdentifier"},{"text":", ","kind":"text"},{"text":"as","kind":"externalParam"},{"text":": ","kind":"text"},{"preciseIdentifier":"s:10Foundation4UUIDV","text":"UUID","kind":"typeIdentifier"},{"text":".Type) ","kind":"text"},{"text":"throws","kind":"keyword"},{"text":" -> [","kind":"text"},{"preciseIdentifier":"s:10Foundation4UUIDV","text":"UUID","kind":"typeIdentifier"},{"text":"]","kind":"text"}],"abstract":[{"type":"text","text":"Return parameter with specified id as a certain type"}],"role":"symbol","url":"\/documentation\/hummingbirdcore\/flatdictionary\/requireall(_:as:)-3sj8s","kind":"symbol","type":"topic","conformance":{"constraints":[{"type":"codeVoice","code":"Key"},{"text":" is ","type":"text"},{"type":"codeVoice","code":"Substring"},{"text":" and ","type":"text"},{"type":"codeVoice","code":"Value"},{"text":" is ","type":"text"},{"type":"codeVoice","code":"Substring"},{"text":".","type":"text"}],"conformancePrefix":[{"text":"Conforms when","type":"text"}],"availabilityPrefix":[{"text":"Available when","type":"text"}]},"title":"requireAll(_:as:)","identifier":"doc:\/\/com.opticalaberration.hummingbird\/documentation\/HummingbirdCore\/FlatDictionary\/requireAll(_:as:)-3sj8s"},"doc://com.opticalaberration.hummingbird/documentation/HummingbirdCore/FlatDictionary/requireAll(_:as:)-52rco":{"abstract":[{"text":"Return parameter with specified id as a certain type","type":"text"}],"type":"topic","fragments":[{"text":"func","kind":"keyword"},{"kind":"text","text":" "},{"kind":"identifier","text":"requireAll"},{"text":"<","kind":"text"},{"kind":"genericParameter","text":"T"},{"text":">(","kind":"text"},{"text":"String","preciseIdentifier":"s:SS","kind":"typeIdentifier"},{"text":", ","kind":"text"},{"kind":"externalParam","text":"as"},{"text":": ","kind":"text"},{"kind":"typeIdentifier","text":"T","preciseIdentifier":"s:15HummingbirdCore14FlatDictionaryV0A0SsRszSsRs_rlE10requireAll_2asSayqd__GSS_qd__mtKs25LosslessStringConvertibleRd__lF1TL_qd__mfp"},{"text":".Type) ","kind":"text"},{"text":"throws","kind":"keyword"},{"kind":"text","text":" -> ["},{"preciseIdentifier":"s:15HummingbirdCore14FlatDictionaryV0A0SsRszSsRs_rlE10requireAll_2asSayqd__GSS_qd__mtKs25LosslessStringConvertibleRd__lF1TL_qd__mfp","text":"T","kind":"typeIdentifier"},{"kind":"text","text":"]"}],"conformance":{"constraints":[{"code":"Key","type":"codeVoice"},{"text":" is ","type":"text"},{"code":"Substring","type":"codeVoice"},{"text":" and ","type":"text"},{"code":"Value","type":"codeVoice"},{"text":" is ","type":"text"},{"type":"codeVoice","code":"Substring"},{"text":".","type":"text"}],"availabilityPrefix":[{"text":"Available when","type":"text"}],"conformancePrefix":[{"text":"Conforms when","type":"text"}]},"identifier":"doc:\/\/com.opticalaberration.hummingbird\/documentation\/HummingbirdCore\/FlatDictionary\/requireAll(_:as:)-52rco","title":"requireAll(_:as:)","kind":"symbol","role":"symbol","url":"\/documentation\/hummingbirdcore\/flatdictionary\/requireall(_:as:)-52rco"},"doc://com.opticalaberration.hummingbird/documentation/HummingbirdCore/FlatDictionary/get(_:as:)-5ewlr":{"conformance":{"constraints":[{"code":"Key","type":"codeVoice"},{"text":" is ","type":"text"},{"code":"Substring","type":"codeVoice"},{"text":" and ","type":"text"},{"code":"Value","type":"codeVoice"},{"text":" is ","type":"text"},{"code":"Substring","type":"codeVoice"},{"text":".","type":"text"}],"conformancePrefix":[{"text":"Conforms when","type":"text"}],"availabilityPrefix":[{"text":"Available when","type":"text"}]},"abstract":[{"type":"text","text":"Return parameter with specified id as a certain type"}],"url":"\/documentation\/hummingbirdcore\/flatdictionary\/get(_:as:)-5ewlr","role":"symbol","type":"topic","identifier":"doc:\/\/com.opticalaberration.hummingbird\/documentation\/HummingbirdCore\/FlatDictionary\/get(_:as:)-5ewlr","kind":"symbol","fragments":[{"kind":"keyword","text":"func"},{"kind":"text","text":" "},{"text":"get","kind":"identifier"},{"text":"(","kind":"text"},{"text":"String","preciseIdentifier":"s:SS","kind":"typeIdentifier"},{"text":", ","kind":"text"},{"text":"as","kind":"externalParam"},{"text":": ","kind":"text"},{"text":"UUID","preciseIdentifier":"s:10Foundation4UUIDV","kind":"typeIdentifier"},{"text":".Type) -> ","kind":"text"},{"text":"UUID","preciseIdentifier":"s:10Foundation4UUIDV","kind":"typeIdentifier"},{"text":"?","kind":"text"}],"title":"get(_:as:)"},"doc://com.opticalaberration.hummingbird/documentation/HummingbirdCore":{"url":"\/documentation\/hummingbirdcore","type":"topic","images":[{"type":"icon","identifier":"logo.png"}],"role":"collection","title":"HummingbirdCore","identifier":"doc:\/\/com.opticalaberration.hummingbird\/documentation\/HummingbirdCore","abstract":[{"type":"text","text":"Swift NIO based HTTP server."}],"kind":"symbol"},"doc://com.opticalaberration.hummingbird/documentation/HummingbirdCore/FlatDictionary/recursiveCaptureKey":{"identifier":"doc:\/\/com.opticalaberration.hummingbird\/documentation\/HummingbirdCore\/FlatDictionary\/recursiveCaptureKey","fragments":[{"kind":"keyword","text":"static"},{"kind":"text","text":" "},{"kind":"keyword","text":"let"},{"kind":"text","text":" "},{"kind":"identifier","text":"recursiveCaptureKey"},{"kind":"text","text":": "},{"kind":"typeIdentifier","preciseIdentifier":"s:Ss","text":"Substring"}],"title":"recursiveCaptureKey","url":"\/documentation\/hummingbirdcore\/flatdictionary\/recursivecapturekey","role":"symbol","type":"topic","kind":"symbol","abstract":[],"conformance":{"availabilityPrefix":[{"type":"text","text":"Available when"}],"conformancePrefix":[{"text":"Conforms when","type":"text"}],"constraints":[{"code":"Key","type":"codeVoice"},{"text":" is ","type":"text"},{"code":"Substring","type":"codeVoice"},{"text":" and ","type":"text"},{"code":"Value","type":"codeVoice"},{"text":" is ","type":"text"},{"code":"Substring","type":"codeVoice"},{"text":".","type":"text"}]}},"doc://com.opticalaberration.hummingbird/documentation/HummingbirdCore/FlatDictionary/init()":{"fragments":[{"text":"init","kind":"identifier"},{"text":"()","kind":"text"}],"abstract":[{"text":"Create a new FlatDictionary","type":"text"}],"role":"symbol","url":"\/documentation\/hummingbirdcore\/flatdictionary\/init()","kind":"symbol","type":"topic","title":"init()","identifier":"doc:\/\/com.opticalaberration.hummingbird\/documentation\/HummingbirdCore\/FlatDictionary\/init()"},"doc://com.opticalaberration.hummingbird/documentation/HummingbirdCore/FlatDictionary/subscript(_:)-2eyqb":{"fragments":[{"text":"subscript","kind":"keyword"},{"text":"(","kind":"text"},{"text":"Key","preciseIdentifier":"s:15HummingbirdCore14FlatDictionaryV3Keyxmfp","kind":"typeIdentifier"},{"text":") -> ","kind":"text"},{"preciseIdentifier":"s:15HummingbirdCore14FlatDictionaryV5Valueq_mfp","text":"Value","kind":"typeIdentifier"},{"text":"?","kind":"text"}],"abstract":[{"text":"Access the value associated with a given key for reading and writing","type":"text"}],"role":"symbol","url":"\/documentation\/hummingbirdcore\/flatdictionary\/subscript(_:)-2eyqb","kind":"symbol","type":"topic","title":"subscript(_:)","identifier":"doc:\/\/com.opticalaberration.hummingbird\/documentation\/HummingbirdCore\/FlatDictionary\/subscript(_:)-2eyqb"},"doc://com.opticalaberration.hummingbird/documentation/HummingbirdCore/FlatDictionary/append(key:value:)":{"identifier":"doc:\/\/com.opticalaberration.hummingbird\/documentation\/HummingbirdCore\/FlatDictionary\/append(key:value:)","fragments":[{"text":"func","kind":"keyword"},{"text":" ","kind":"text"},{"text":"append","kind":"identifier"},{"text":"(","kind":"text"},{"text":"key","kind":"externalParam"},{"text":": ","kind":"text"},{"text":"Key","kind":"typeIdentifier","preciseIdentifier":"s:15HummingbirdCore14FlatDictionaryV3Keyxmfp"},{"text":", ","kind":"text"},{"text":"value","kind":"externalParam"},{"text":": ","kind":"text"},{"text":"Value","preciseIdentifier":"s:15HummingbirdCore14FlatDictionaryV5Valueq_mfp","kind":"typeIdentifier"},{"text":")","kind":"text"}],"kind":"symbol","type":"topic","title":"append(key:value:)","abstract":[{"text":"Append a new key value pair to the list of key value pairs","type":"text"}],"url":"\/documentation\/hummingbirdcore\/flatdictionary\/append(key:value:)","role":"symbol"},"doc://com.opticalaberration.hummingbird/documentation/HummingbirdCore/FlatDictionary/subscript(values:)":{"url":"\/documentation\/hummingbirdcore\/flatdictionary\/subscript(values:)","abstract":[{"text":"Return all the values, associated with a given key","type":"text"}],"identifier":"doc:\/\/com.opticalaberration.hummingbird\/documentation\/HummingbirdCore\/FlatDictionary\/subscript(values:)","title":"subscript(values:)","role":"symbol","kind":"symbol","fragments":[{"text":"subscript","kind":"keyword"},{"text":"(","kind":"text"},{"text":"values","kind":"externalParam"},{"text":" _: ","kind":"text"},{"text":"Key","kind":"typeIdentifier","preciseIdentifier":"s:15HummingbirdCore14FlatDictionaryV3Keyxmfp"},{"text":") -> [","kind":"text"},{"text":"Value","kind":"typeIdentifier","preciseIdentifier":"s:15HummingbirdCore14FlatDictionaryV5Valueq_mfp"},{"text":"]","kind":"text"}],"type":"topic"},"doc://com.opticalaberration.hummingbird/documentation/HummingbirdCore/FlatDictionary/init(dictionaryLiteral:)":{"abstract":[{"type":"text","text":"Create a new FlatDictionary initialized with a dictionary literal"}],"role":"symbol","fragments":[{"text":"init","kind":"identifier"},{"text":"(","kind":"text"},{"text":"dictionaryLiteral","kind":"externalParam"},{"text":": (","kind":"text"},{"text":"Key","kind":"typeIdentifier","preciseIdentifier":"s:15HummingbirdCore14FlatDictionaryV3Keyxmfp"},{"text":", ","kind":"text"},{"text":"Value","kind":"typeIdentifier","preciseIdentifier":"s:15HummingbirdCore14FlatDictionaryV5Valueq_mfp"},{"text":")...)","kind":"text"}],"kind":"symbol","identifier":"doc:\/\/com.opticalaberration.hummingbird\/documentation\/HummingbirdCore\/FlatDictionary\/init(dictionaryLiteral:)","type":"topic","url":"\/documentation\/hummingbirdcore\/flatdictionary\/init(dictionaryliteral:)","title":"init(dictionaryLiteral:)"},"doc://com.opticalaberration.hummingbird/documentation/HummingbirdCore/FlatDictionary/require(_:as:)-zo5p":{"url":"\/documentation\/hummingbirdcore\/flatdictionary\/require(_:as:)-zo5p","type":"topic","abstract":[{"type":"text","text":"Return parameter with specified id as a certain type"}],"conformance":{"constraints":[{"type":"codeVoice","code":"Key"},{"type":"text","text":" is "},{"type":"codeVoice","code":"Substring"},{"type":"text","text":" and "},{"type":"codeVoice","code":"Value"},{"text":" is ","type":"text"},{"type":"codeVoice","code":"Substring"},{"text":".","type":"text"}],"availabilityPrefix":[{"type":"text","text":"Available when"}],"conformancePrefix":[{"type":"text","text":"Conforms when"}]},"role":"symbol","kind":"symbol","identifier":"doc:\/\/com.opticalaberration.hummingbird\/documentation\/HummingbirdCore\/FlatDictionary\/require(_:as:)-zo5p","fragments":[{"kind":"keyword","text":"func"},{"kind":"text","text":" "},{"kind":"identifier","text":"require"},{"kind":"text","text":"<"},{"kind":"genericParameter","text":"T"},{"kind":"text","text":">("},{"kind":"typeIdentifier","preciseIdentifier":"s:SS","text":"String"},{"kind":"text","text":", "},{"kind":"externalParam","text":"as"},{"kind":"text","text":": "},{"kind":"typeIdentifier","text":"T","preciseIdentifier":"s:15HummingbirdCore14FlatDictionaryV0A0SsRszSsRs_rlE7require_2asqd__SS_qd__mtKSYRd__SS8RawValueRtd__lF1TL_qd__mfp"},{"kind":"text","text":".Type) "},{"kind":"keyword","text":"throws"},{"kind":"text","text":" -> "},{"kind":"typeIdentifier","text":"T","preciseIdentifier":"s:15HummingbirdCore14FlatDictionaryV0A0SsRszSsRs_rlE7require_2asqd__SS_qd__mtKSYRd__SS8RawValueRtd__lF1TL_qd__mfp"}],"title":"require(_:as:)"},"doc://com.opticalaberration.hummingbird/documentation/HummingbirdCore/FlatDictionary/getCatchAll()":{"type":"topic","abstract":[{"type":"text","text":"Return path elements caught by recursive capture"}],"fragments":[{"kind":"keyword","text":"func"},{"kind":"text","text":" "},{"kind":"identifier","text":"getCatchAll"},{"kind":"text","text":"() -> ["},{"kind":"typeIdentifier","preciseIdentifier":"s:Ss","text":"Substring"},{"kind":"text","text":"]"}],"conformance":{"constraints":[{"code":"Key","type":"codeVoice"},{"type":"text","text":" is "},{"code":"Substring","type":"codeVoice"},{"type":"text","text":" and "},{"code":"Value","type":"codeVoice"},{"type":"text","text":" is "},{"code":"Substring","type":"codeVoice"},{"type":"text","text":"."}],"availabilityPrefix":[{"type":"text","text":"Available when"}],"conformancePrefix":[{"type":"text","text":"Conforms when"}]},"title":"getCatchAll()","identifier":"doc:\/\/com.opticalaberration.hummingbird\/documentation\/HummingbirdCore\/FlatDictionary\/getCatchAll()","url":"\/documentation\/hummingbirdcore\/flatdictionary\/getcatchall()","role":"symbol","kind":"symbol"},"doc://com.opticalaberration.hummingbird/documentation/HummingbirdCore/FlatDictionary/getAll(_:as:)-4h655":{"fragments":[{"kind":"keyword","text":"func"},{"kind":"text","text":" "},{"kind":"identifier","text":"getAll"},{"kind":"text","text":"<"},{"kind":"genericParameter","text":"T"},{"text":">(","kind":"text"},{"preciseIdentifier":"s:SS","text":"String","kind":"typeIdentifier"},{"text":", ","kind":"text"},{"text":"as","kind":"externalParam"},{"text":": ","kind":"text"},{"preciseIdentifier":"s:15HummingbirdCore14FlatDictionaryV0A0SsRszSsRs_rlE6getAll_2asSayqd__GSS_qd__mts25LosslessStringConvertibleRd__lF1TL_qd__mfp","text":"T","kind":"typeIdentifier"},{"text":".Type) -> [","kind":"text"},{"text":"T","kind":"typeIdentifier","preciseIdentifier":"s:15HummingbirdCore14FlatDictionaryV0A0SsRszSsRs_rlE6getAll_2asSayqd__GSS_qd__mts25LosslessStringConvertibleRd__lF1TL_qd__mfp"},{"text":"]","kind":"text"}],"identifier":"doc:\/\/com.opticalaberration.hummingbird\/documentation\/HummingbirdCore\/FlatDictionary\/getAll(_:as:)-4h655","conformance":{"conformancePrefix":[{"text":"Conforms when","type":"text"}],"availabilityPrefix":[{"text":"Available when","type":"text"}],"constraints":[{"code":"Key","type":"codeVoice"},{"text":" is ","type":"text"},{"code":"Substring","type":"codeVoice"},{"text":" and ","type":"text"},{"code":"Value","type":"codeVoice"},{"text":" is ","type":"text"},{"code":"Substring","type":"codeVoice"},{"text":".","type":"text"}]},"role":"symbol","abstract":[{"text":"Return parameter with specified id as a certain type","type":"text"}],"title":"getAll(_:as:)","type":"topic","url":"\/documentation\/hummingbirdcore\/flatdictionary\/getall(_:as:)-4h655","kind":"symbol"},"doc://com.opticalaberration.hummingbird/Sl":{"type":"unresolvable","identifier":"doc:\/\/com.opticalaberration.hummingbird\/Sl","title":"Swift.Collection"},"logo.png":{"type":"image","variants":[{"url":"\/images\/logo.png","traits":["1x","light"]}],"alt":null,"identifier":"logo.png"},"doc://com.opticalaberration.hummingbird/documentation/HummingbirdCore/FlatDictionary/init(_:)":{"role":"symbol","kind":"symbol","abstract":[{"text":"Create a new FlatDictionary from an array of key value pairs","type":"text"}],"type":"topic","fragments":[{"text":"init","kind":"identifier"},{"text":"([","kind":"text"},{"text":"Element","preciseIdentifier":"s:15HummingbirdCore14FlatDictionaryV7Elementa","kind":"typeIdentifier"},{"text":"])","kind":"text"}],"identifier":"doc:\/\/com.opticalaberration.hummingbird\/documentation\/HummingbirdCore\/FlatDictionary\/init(_:)","title":"init(_:)","url":"\/documentation\/hummingbirdcore\/flatdictionary\/init(_:)"},"doc://com.opticalaberration.hummingbird/documentation/HummingbirdCore/FlatDictionary/require(_:as:)-8wfem":{"type":"topic","url":"\/documentation\/hummingbirdcore\/flatdictionary\/require(_:as:)-8wfem","fragments":[{"kind":"keyword","text":"func"},{"text":" ","kind":"text"},{"text":"require","kind":"identifier"},{"text":"<","kind":"text"},{"text":"T","kind":"genericParameter"},{"text":">(","kind":"text"},{"preciseIdentifier":"s:SS","text":"String","kind":"typeIdentifier"},{"text":", ","kind":"text"},{"text":"as","kind":"externalParam"},{"text":": ","kind":"text"},{"preciseIdentifier":"s:15HummingbirdCore14FlatDictionaryV0A0SsRszSsRs_rlE7require_2asqd__SS_qd__mtKs25LosslessStringConvertibleRd__lF1TL_qd__mfp","text":"T","kind":"typeIdentifier"},{"text":".Type) ","kind":"text"},{"text":"throws","kind":"keyword"},{"text":" -> ","kind":"text"},{"preciseIdentifier":"s:15HummingbirdCore14FlatDictionaryV0A0SsRszSsRs_rlE7require_2asqd__SS_qd__mtKs25LosslessStringConvertibleRd__lF1TL_qd__mfp","text":"T","kind":"typeIdentifier"}],"role":"symbol","conformance":{"constraints":[{"code":"Key","type":"codeVoice"},{"type":"text","text":" is "},{"code":"Substring","type":"codeVoice"},{"type":"text","text":" and "},{"code":"Value","type":"codeVoice"},{"type":"text","text":" is "},{"code":"Substring","type":"codeVoice"},{"type":"text","text":"."}],"conformancePrefix":[{"type":"text","text":"Conforms when"}],"availabilityPrefix":[{"type":"text","text":"Available when"}]},"abstract":[{"type":"text","text":"Return parameter with specified id as a certain type"}],"kind":"symbol","identifier":"doc:\/\/com.opticalaberration.hummingbird\/documentation\/HummingbirdCore\/FlatDictionary\/require(_:as:)-8wfem","title":"require(_:as:)"},"doc://com.opticalaberration.hummingbird/documentation/HummingbirdCore/FlatDictionary/get(_:)":{"type":"topic","kind":"symbol","url":"\/documentation\/hummingbirdcore\/flatdictionary\/get(_:)","role":"symbol","conformance":{"constraints":[{"type":"codeVoice","code":"Key"},{"text":" is ","type":"text"},{"type":"codeVoice","code":"Substring"},{"text":" and ","type":"text"},{"type":"codeVoice","code":"Value"},{"text":" is ","type":"text"},{"type":"codeVoice","code":"Substring"},{"text":".","type":"text"}],"conformancePrefix":[{"text":"Conforms when","type":"text"}],"availabilityPrefix":[{"text":"Available when","type":"text"}]},"identifier":"doc:\/\/com.opticalaberration.hummingbird\/documentation\/HummingbirdCore\/FlatDictionary\/get(_:)","abstract":[{"text":"Return parameter with specified id","type":"text"}],"fragments":[{"kind":"keyword","text":"func"},{"kind":"text","text":" "},{"kind":"identifier","text":"get"},{"kind":"text","text":"("},{"kind":"typeIdentifier","text":"String","preciseIdentifier":"s:SS"},{"kind":"text","text":") -> "},{"text":"String","kind":"typeIdentifier","preciseIdentifier":"s:SS"},{"text":"?","kind":"text"}],"title":"get(_:)"},"doc://com.opticalaberration.hummingbird/documentation/HummingbirdCore/FlatDictionary/getAll(_:as:)-261y8":{"title":"getAll(_:as:)","identifier":"doc:\/\/com.opticalaberration.hummingbird\/documentation\/HummingbirdCore\/FlatDictionary\/getAll(_:as:)-261y8","url":"\/documentation\/hummingbirdcore\/flatdictionary\/getall(_:as:)-261y8","type":"topic","role":"symbol","fragments":[{"text":"func","kind":"keyword"},{"text":" ","kind":"text"},{"text":"getAll","kind":"identifier"},{"text":"<","kind":"text"},{"text":"T","kind":"genericParameter"},{"text":">(","kind":"text"},{"text":"String","kind":"typeIdentifier","preciseIdentifier":"s:SS"},{"text":", ","kind":"text"},{"text":"as","kind":"externalParam"},{"text":": ","kind":"text"},{"text":"T","kind":"typeIdentifier","preciseIdentifier":"s:15HummingbirdCore14FlatDictionaryV0A0SsRszSsRs_rlE6getAll_2asSayqd__GSS_qd__mtSYRd__SS8RawValueRtd__lF1TL_qd__mfp"},{"text":".Type) -> [","kind":"text"},{"text":"T","kind":"typeIdentifier","preciseIdentifier":"s:15HummingbirdCore14FlatDictionaryV0A0SsRszSsRs_rlE6getAll_2asSayqd__GSS_qd__mtSYRd__SS8RawValueRtd__lF1TL_qd__mfp"},{"text":"]","kind":"text"}],"abstract":[{"text":"Return parameter with specified id as a certain type","type":"text"}],"kind":"symbol","conformance":{"availabilityPrefix":[{"type":"text","text":"Available when"}],"constraints":[{"code":"Key","type":"codeVoice"},{"type":"text","text":" is "},{"code":"Substring","type":"codeVoice"},{"type":"text","text":" and "},{"code":"Value","type":"codeVoice"},{"type":"text","text":" is "},{"type":"codeVoice","code":"Substring"},{"text":".","type":"text"}],"conformancePrefix":[{"type":"text","text":"Conforms when"}]}},"doc://com.opticalaberration.hummingbird/documentation/HummingbirdCore/FlatDictionary/get(_:as:)-2owlj":{"fragments":[{"kind":"keyword","text":"func"},{"kind":"text","text":" "},{"kind":"identifier","text":"get"},{"kind":"text","text":"<"},{"kind":"genericParameter","text":"T"},{"kind":"text","text":">("},{"kind":"typeIdentifier","text":"String","preciseIdentifier":"s:SS"},{"kind":"text","text":", "},{"kind":"externalParam","text":"as"},{"kind":"text","text":": "},{"kind":"typeIdentifier","text":"T","preciseIdentifier":"s:15HummingbirdCore14FlatDictionaryV0A0SsRszSsRs_rlE3get_2asqd__SgSS_qd__mtSYRd__SS8RawValueRtd__lF1TL_qd__mfp"},{"kind":"text","text":".Type) -> "},{"kind":"typeIdentifier","text":"T","preciseIdentifier":"s:15HummingbirdCore14FlatDictionaryV0A0SsRszSsRs_rlE3get_2asqd__SgSS_qd__mtSYRd__SS8RawValueRtd__lF1TL_qd__mfp"},{"kind":"text","text":"?"}],"type":"topic","abstract":[{"type":"text","text":"Return parameter with specified id as a certain type"}],"kind":"symbol","title":"get(_:as:)","url":"\/documentation\/hummingbirdcore\/flatdictionary\/get(_:as:)-2owlj","role":"symbol","conformance":{"constraints":[{"code":"Key","type":"codeVoice"},{"text":" is ","type":"text"},{"code":"Substring","type":"codeVoice"},{"text":" and ","type":"text"},{"code":"Value","type":"codeVoice"},{"text":" is ","type":"text"},{"code":"Substring","type":"codeVoice"},{"text":".","type":"text"}],"conformancePrefix":[{"text":"Conforms when","type":"text"}],"availabilityPrefix":[{"text":"Available when","type":"text"}]},"identifier":"doc:\/\/com.opticalaberration.hummingbird\/documentation\/HummingbirdCore\/FlatDictionary\/get(_:as:)-2owlj"},"doc://com.opticalaberration.hummingbird/s30ExpressibleByDictionaryLiteralP":{"identifier":"doc:\/\/com.opticalaberration.hummingbird\/s30ExpressibleByDictionaryLiteralP","type":"unresolvable","title":"Swift.ExpressibleByDictionaryLiteral"},"doc://com.opticalaberration.hummingbird/documentation/HummingbirdCore/FlatDictionary/require(_:)":{"fragments":[{"text":"func","kind":"keyword"},{"text":" ","kind":"text"},{"text":"require","kind":"identifier"},{"text":"(","kind":"text"},{"text":"String","kind":"typeIdentifier","preciseIdentifier":"s:SS"},{"text":") ","kind":"text"},{"text":"throws","kind":"keyword"},{"text":" -> ","kind":"text"},{"text":"String","kind":"typeIdentifier","preciseIdentifier":"s:SS"}],"type":"topic","identifier":"doc:\/\/com.opticalaberration.hummingbird\/documentation\/HummingbirdCore\/FlatDictionary\/require(_:)","kind":"symbol","title":"require(_:)","url":"\/documentation\/hummingbirdcore\/flatdictionary\/require(_:)","conformance":{"constraints":[{"code":"Key","type":"codeVoice"},{"text":" is ","type":"text"},{"code":"Substring","type":"codeVoice"},{"text":" and ","type":"text"},{"code":"Value","type":"codeVoice"},{"text":" is ","type":"text"},{"code":"Substring","type":"codeVoice"},{"text":".","type":"text"}],"conformancePrefix":[{"text":"Conforms when","type":"text"}],"availabilityPrefix":[{"text":"Available when","type":"text"}]},"role":"symbol","abstract":[{"type":"text","text":"Return parameter with specified id"}]},"doc://com.opticalaberration.hummingbird/documentation/HummingbirdCore/FlatDictionary/Index":{"navigatorTitle":[{"text":"Index","kind":"identifier"}],"url":"\/documentation\/hummingbirdcore\/flatdictionary\/index","identifier":"doc:\/\/com.opticalaberration.hummingbird\/documentation\/HummingbirdCore\/FlatDictionary\/Index","role":"symbol","kind":"symbol","type":"topic","title":"FlatDictionary.Index","abstract":[],"fragments":[{"text":"typealias","kind":"keyword"},{"text":" ","kind":"text"},{"text":"Index","kind":"identifier"}]},"doc://com.opticalaberration.hummingbird/documentation/HummingbirdCore/FlatDictionary/getAll(_:)":{"url":"\/documentation\/hummingbirdcore\/flatdictionary\/getall(_:)","abstract":[{"text":"Return parameter with specified id as a certain type","type":"text"}],"kind":"symbol","fragments":[{"kind":"keyword","text":"func"},{"kind":"text","text":" "},{"kind":"identifier","text":"getAll"},{"text":"(","kind":"text"},{"text":"String","kind":"typeIdentifier","preciseIdentifier":"s:SS"},{"text":") -> [","kind":"text"},{"text":"String","kind":"typeIdentifier","preciseIdentifier":"s:SS"},{"text":"]","kind":"text"}],"title":"getAll(_:)","identifier":"doc:\/\/com.opticalaberration.hummingbird\/documentation\/HummingbirdCore\/FlatDictionary\/getAll(_:)","type":"topic","role":"symbol","conformance":{"conformancePrefix":[{"type":"text","text":"Conforms when"}],"constraints":[{"code":"Key","type":"codeVoice"},{"type":"text","text":" is "},{"code":"Substring","type":"codeVoice"},{"type":"text","text":" and "},{"code":"Value","type":"codeVoice"},{"type":"text","text":" is "},{"code":"Substring","type":"codeVoice"},{"type":"text","text":"."}],"availabilityPrefix":[{"type":"text","text":"Available when"}]}},"doc://com.opticalaberration.hummingbird/documentation/HummingbirdCore/FlatDictionary/setCatchAll(_:)":{"conformance":{"availabilityPrefix":[{"text":"Available when","type":"text"}],"constraints":[{"type":"codeVoice","code":"Key"},{"text":" is ","type":"text"},{"type":"codeVoice","code":"Substring"},{"text":" and ","type":"text"},{"type":"codeVoice","code":"Value"},{"text":" is ","type":"text"},{"type":"codeVoice","code":"Substring"},{"text":".","type":"text"}],"conformancePrefix":[{"text":"Conforms when","type":"text"}]},"abstract":[{"type":"text","text":"Set path components caught by recursive capture"}],"fragments":[{"kind":"keyword","text":"func"},{"kind":"text","text":" "},{"kind":"identifier","text":"setCatchAll"},{"kind":"text","text":"("},{"kind":"typeIdentifier","text":"Substring","preciseIdentifier":"s:Ss"},{"kind":"text","text":")"}],"url":"\/documentation\/hummingbirdcore\/flatdictionary\/setcatchall(_:)","role":"symbol","identifier":"doc:\/\/com.opticalaberration.hummingbird\/documentation\/HummingbirdCore\/FlatDictionary\/setCatchAll(_:)","type":"topic","title":"setCatchAll(_:)","kind":"symbol"},"doc://com.opticalaberration.hummingbird/documentation/HummingbirdCore/FlatDictionary/has(_:)":{"role":"symbol","url":"\/documentation\/hummingbirdcore\/flatdictionary\/has(_:)","kind":"symbol","fragments":[{"kind":"keyword","text":"func"},{"kind":"text","text":" "},{"kind":"identifier","text":"has"},{"kind":"text","text":"("},{"kind":"typeIdentifier","preciseIdentifier":"s:15HummingbirdCore14FlatDictionaryV3Keyxmfp","text":"Key"},{"kind":"text","text":") -> "},{"kind":"typeIdentifier","preciseIdentifier":"s:Sb","text":"Bool"}],"abstract":[{"type":"text","text":"Return if dictionary has this value"}],"type":"topic","identifier":"doc:\/\/com.opticalaberration.hummingbird\/documentation\/HummingbirdCore\/FlatDictionary\/has(_:)","title":"has(_:)"},"doc://com.opticalaberration.hummingbird/documentation/HummingbirdCore/FlatDictionary/requireAll(_:as:)-8n9if":{"abstract":[{"type":"text","text":"Return parameter with specified id as a certain type"}],"type":"topic","fragments":[{"kind":"keyword","text":"func"},{"kind":"text","text":" "},{"kind":"identifier","text":"requireAll"},{"kind":"text","text":"<"},{"kind":"genericParameter","text":"T"},{"kind":"text","text":">("},{"kind":"typeIdentifier","preciseIdentifier":"s:SS","text":"String"},{"kind":"text","text":", "},{"kind":"externalParam","text":"as"},{"kind":"text","text":": "},{"text":"T","preciseIdentifier":"s:15HummingbirdCore14FlatDictionaryV0A0SsRszSsRs_rlE10requireAll_2asSayqd__GSS_qd__mtKSYRd__SS8RawValueRtd__lF1TL_qd__mfp","kind":"typeIdentifier"},{"text":".Type) ","kind":"text"},{"text":"throws","kind":"keyword"},{"text":" -> [","kind":"text"},{"text":"T","preciseIdentifier":"s:15HummingbirdCore14FlatDictionaryV0A0SsRszSsRs_rlE10requireAll_2asSayqd__GSS_qd__mtKSYRd__SS8RawValueRtd__lF1TL_qd__mfp","kind":"typeIdentifier"},{"text":"]","kind":"text"}],"conformance":{"availabilityPrefix":[{"type":"text","text":"Available when"}],"constraints":[{"type":"codeVoice","code":"Key"},{"type":"text","text":" is "},{"type":"codeVoice","code":"Substring"},{"type":"text","text":" and "},{"type":"codeVoice","code":"Value"},{"text":" is ","type":"text"},{"type":"codeVoice","code":"Substring"},{"text":".","type":"text"}],"conformancePrefix":[{"type":"text","text":"Conforms when"}]},"identifier":"doc:\/\/com.opticalaberration.hummingbird\/documentation\/HummingbirdCore\/FlatDictionary\/requireAll(_:as:)-8n9if","url":"\/documentation\/hummingbirdcore\/flatdictionary\/requireall(_:as:)-8n9if","role":"symbol","title":"requireAll(_:as:)","kind":"symbol"}}}